Biopyutils/Comm.py
Biopyutils/Epic.py
Biopyutils/Exprsn.py
Biopyutils/Mut.py
Biopyutils/Protein.py
Biopyutils/__init__.py
Biopyutils/R/BatchRemoval.R
Biopyutils/R/GSVA.R
Biopyutils/R/LimmaVoom.R
Biopyutils/R/immunedeconv.R
Biopyutils/R/utils.R
Biopyutils/R/immunedeconv_data/CIBERSORT.R
Biopyutils/R/immunedeconv_data/LM22.txt
Biopyutils/R/immunedeconv_data/avgTPM.Rdata
Biopyutils/R/immunedeconv_data/mcpcounter_genes.txt
Biopyutils/R/immunedeconv_data/mm2hs.Rdata
Biopyutils/R/immunedeconv_data/timer_geneMarker.Rdata
Biopyutils/R/immunedeconv_data/timer_pureImmune.Rdata
Biopyutils/data/geneId_hg_ENSG.pickle.gz
Biopyutils/data/geneId_hg_Entrez.pickle.gz
Biopyutils/data/geneId_hg_Name.pickle.gz
Biopyutils/data/geneId_hg_Symbol.pickle.gz
Biopyutils/data/geneId_mm_ENSG.pickle.gz
Biopyutils/data/geneId_mm_Entrez.pickle.gz
Biopyutils/data/geneId_mm_Name.pickle.gz
Biopyutils/data/geneId_mm_Symbol.pickle.gz
Biopyutils/data/species_hg-mm_ENSG.pickle.gz
Biopyutils/data/species_hg-mm_Entrez.pickle.gz
Biopyutils-0.2.0.data/scripts/Biopyutils
Biopyutils-0.2.0.dist-info/LICENSE
Biopyutils-0.2.0.dist-info/METADATA
Biopyutils-0.2.0.dist-info/WHEEL
Biopyutils-0.2.0.dist-info/top_level.txt
Biopyutils-0.2.0.dist-info/RECORD
