Metadata-Version: 2.1
Name: Biopyutils
Version: 0.2.0
Summary: A bionformatic tookits
Home-page: https://jingxinfu.github.io/Biopyutils
Author: Jingxin Fu
Author-email: jingxinfu.tj@gmail.com
License: UNKNOWN
Keywords: Gene ID Convertor,Bioinformatics,Genomics,Computational Biologist
Platform: UNKNOWN
Classifier: Programming Language :: Python
Classifier: License :: OSI Approved :: GNU General Public License v3 or later (GPLv3+)
Classifier: Operating System :: Unix
Classifier: Operating System :: MacOS
Requires-Python: >=3.5
Requires-Dist: pandas (>=0.24)
Requires-Dist: numpy
Requires-Dist: scipy
Requires-Dist: statsmodels
Requires-Dist: scikit-learn
